dodecaphony/__init__.py
dodecaphony/__main__.py
dodecaphony/constants.py
dodecaphony/evaluation.py
dodecaphony/fragment.py
dodecaphony/music_theory.py
dodecaphony/optimization.py
dodecaphony/rendering.py
dodecaphony/transformations.py
dodecaphony/utils.py
dodecaphony/configs/default_config.yml
dodecaphony/configs/sinethesizer_presets.yml
dodecaphony/scoring_functions/__init__.py
dodecaphony/scoring_functions/harmony.py
dodecaphony/scoring_functions/melody.py
dodecaphony/scoring_functions/rhythm.py
dodecaphony-0.2.1.dist-info/LICENSE
dodecaphony-0.2.1.dist-info/METADATA
dodecaphony-0.2.1.dist-info/WHEEL
dodecaphony-0.2.1.dist-info/top_level.txt
dodecaphony-0.2.1.dist-info/RECORD
