Metadata-Version: 2.1
Name: dodecaphony
Version: 0.2.1
Summary: Algorithmic composition of modern classical music in the twelve-tone technique
Author-email: Nikolay Lysenko <nikolay-lysenco@yandex.ru>
Project-URL: Homepage, https://github.com/Nikolay-Lysenko/dodecaphony
Keywords: ai_music,algorithmic_composition,atonality,dodecaphony,serialism,twelve_tone
Classifier: Development Status :: 4 - Beta
Classifier: Intended Audience :: End Users/Desktop
Classifier: Topic :: Artistic Software
Classifier: Topic :: Scientific/Engineering :: Artificial Intelligence
Classifier: License :: OSI Approved :: MIT License
Classifier: Programming Language :: Python :: 3
Requires-Python: >=3.9
License-File: LICENSE
Requires-Dist: pretty-midi
Requires-Dist: PyYAML
Requires-Dist: sinethesizer <0.7,>=0.6
